splashstand/Dockerfile
splashstand/Procfile
splashstand/__init__.py
splashstand/__main__.py
splashstand/cli.py
splashstand/main.py
splashstand/actions/__init__.py
splashstand/adapters/__init__.py
splashstand/adapters/admin/__init__.py
splashstand/adapters/admin/_base.py
splashstand/adapters/admin/sqladmin.py
splashstand/adapters/admin/_templates/base/base.html
splashstand/adapters/admin/_templates/base/js/serviceworker.js
splashstand/adapters/admin/_templates/old/actions.html
splashstand/adapters/admin/_templates/old/analytics.html
splashstand/adapters/admin/_templates/old/content.html
splashstand/adapters/admin/_templates/old/details_modal.html
splashstand/adapters/admin/_templates/old/edit_modal.html
splashstand/adapters/admin/_templates/old/help.html
splashstand/adapters/admin/_templates/old/index.html
splashstand/adapters/admin/_templates/old/layout.html
splashstand/adapters/admin/_templates/old/lib.html
splashstand/adapters/admin/_templates/old/list.html
splashstand/adapters/admin/_templates/old/modal.html
splashstand/adapters/admin/_templates/old/offline.html
splashstand/adapters/admin/_templates/old/preview.html
splashstand/adapters/admin/_templates/old/redis_console.html
splashstand/adapters/admin/_templates/old/redis_response.html
splashstand/adapters/admin/_templates/old/row_actions.html
splashstand/adapters/admin/_templates/old/site_edit.html
splashstand/adapters/admin/_templates/old/static.html
splashstand/adapters/admin/_templates/old/storage_list.html
splashstand/adapters/admin/_templates/old/store.html
splashstand/adapters/admin/_templates/old/support.html
splashstand/adapters/admin/_templates/old/theme_details_modal.html
splashstand/adapters/admin/_templates/old/theme_edit.html
splashstand/adapters/admin/_templates/old/theme_list.html
splashstand/adapters/admin/_templates/webawesome/sqladmin/create.html
splashstand/adapters/admin/_templates/webawesome/sqladmin/details.html
splashstand/adapters/admin/_templates/webawesome/sqladmin/edit.html
splashstand-3.0.10.dist-info/METADATA
splashstand-3.0.10.dist-info/WHEEL
splashstand-3.0.10.dist-info/licenses/LICENSE
splashstand-3.0.10.dist-info/RECORD
