Metadata-Version: 2.4
Name: splashstand
Version: 3.0.10
Project-URL: Homepage, https://gitlab.com/lesleslie/splashstand
Project-URL: Documentation, https://gitlab.com/lesleslie/splashstand
Project-URL: Repository, https://gitlab.com/lesleslie/splashstand
Author-email: lesleslie <les@wedgwoodwebworks.com>
Maintainer-email: lesleslie <les@wedgwoodwebworks.com>
License: BSD-3-Clause
License-File: LICENSE
Keywords: htmx,httpx,jinja,pydantic,sqladmin,sqlmodel,starlette
Classifier: Development Status :: 3 - Alpha
Classifier: Framework :: AsyncIO
Classifier: Framework :: Pydantic
Classifier: Framework :: Pydantic :: 2
Classifier: License :: OSI Approved :: BSD License
Classifier: Operating System :: OS Independent
Classifier: Programming Language :: Python
Classifier: Programming Language :: Python :: 3.13
Classifier: Topic :: Internet :: WWW/HTTP :: Dynamic Content
Classifier: Topic :: Internet :: WWW/HTTP :: Dynamic Content :: Content Management System
Classifier: Topic :: Internet :: WWW/HTTP :: Site Management
Classifier: Typing :: Typed
Requires-Python: >=3.13
Requires-Dist: acb[cache,dns,monitoring,requests,secret,smtp,sql,storage]
Requires-Dist: alive-progress>=3.2.0
Requires-Dist: fastblocks[admin,monitoring,sitemap]
Requires-Dist: jinja2-inflection>=0.4.0
Requires-Dist: phonenumbers>=9.0.8
Requires-Dist: pydantic[email]>=2.11.7
Requires-Dist: uuid-utils>=0.11.0
Requires-Dist: uv>=0.7.19
Provides-Extra: analytics
Requires-Dist: google-analytics-admin>=0.24.1; extra == 'analytics'
Requires-Dist: google-analytics-data>=0.18.19; extra == 'analytics'
Provides-Extra: auth
Requires-Dist: firebase-admin>=6.9.0; extra == 'auth'
Provides-Extra: captcha
Requires-Dist: google-cloud-recaptcha-enterprise>=1.28.2; extra == 'captcha'
